daytona_api_client/__init__.py
daytona_api_client/api_client.py
daytona_api_client/api_response.py
daytona_api_client/configuration.py
daytona_api_client/exceptions.py
daytona_api_client/py.typed
daytona_api_client/rest.py
daytona_api_client/api/__init__.py
daytona_api_client/api/api_keys_api.py
daytona_api_client/api/docker_registry_api.py
daytona_api_client/api/object_storage_api.py
daytona_api_client/api/organizations_api.py
daytona_api_client/api/preview_api.py
daytona_api_client/api/runners_api.py
daytona_api_client/api/sandbox_api.py
daytona_api_client/api/snapshots_api.py
daytona_api_client/api/toolbox_api.py
daytona_api_client/api/users_api.py
daytona_api_client/api/volumes_api.py
daytona_api_client/api/workspace_api.py
daytona_api_client/models/__init__.py
daytona_api_client/models/account_provider.py
daytona_api_client/models/api_key_list.py
daytona_api_client/models/api_key_response.py
daytona_api_client/models/build_info.py
daytona_api_client/models/command.py
daytona_api_client/models/completion_context.py
daytona_api_client/models/completion_item.py
daytona_api_client/models/completion_list.py
daytona_api_client/models/create_api_key.py
daytona_api_client/models/create_build_info.py
daytona_api_client/models/create_docker_registry.py
daytona_api_client/models/create_linked_account.py
daytona_api_client/models/create_organization.py
daytona_api_client/models/create_organization_invitation.py
daytona_api_client/models/create_organization_quota.py
daytona_api_client/models/create_organization_role.py
daytona_api_client/models/create_runner.py
daytona_api_client/models/create_sandbox.py
daytona_api_client/models/create_session_request.py
daytona_api_client/models/create_snapshot.py
daytona_api_client/models/create_user.py
daytona_api_client/models/create_volume.py
daytona_api_client/models/create_workspace.py
daytona_api_client/models/docker_registry.py
daytona_api_client/models/execute_request.py
daytona_api_client/models/execute_response.py
platon_daytona_api_client-0.1.5.dist-info/licenses/LICENSE
platon_daytona_api_client-0.1.5.dist-info/METADATA
platon_daytona_api_client-0.1.5.dist-info/WHEEL
platon_daytona_api_client-0.1.5.dist-info/top_level.txt
platon_daytona_api_client-0.1.5.dist-info/RECORD
