Metadata-Version: 2.4
Name: platon-daytona-api-client
Version: 0.1.5
Summary: Daytona
Home-page: 
Author: Daytona Platforms Inc.
Author-email: support@daytona.com
Keywords: OpenAPI,OpenAPI-Generator,Daytona
License-File: LICENSE
Requires-Dist: urllib3<3.0.0,>=1.25.3
Requires-Dist: python-dateutil>=2.8.2
Requires-Dist: pydantic>=2
Requires-Dist: typing-extensions>=4.7.1
Dynamic: author
Dynamic: author-email
Dynamic: description
Dynamic: description-content-type
Dynamic: keywords
Dynamic: license-file
Dynamic: requires-dist
Dynamic: summary
